genie.conf-19.12-py3.5-nspkg.pth
genie/conf/__init__.py
genie/conf/main.cpython-35m-x86_64-linux-gnu.so
genie/conf/base/__init__.py
genie/conf/base/api.cpython-35m-x86_64-linux-gnu.so
genie/conf/base/attributes.cpython-35m-x86_64-linux-gnu.so
genie/conf/base/base.cpython-35m-x86_64-linux-gnu.so
genie/conf/base/cli.cpython-35m-x86_64-linux-gnu.so
genie/conf/base/config.cpython-35m-x86_64-linux-gnu.so
genie/conf/base/decorator.cpython-35m-x86_64-linux-gnu.so
genie/conf/base/device.cpython-35m-x86_64-linux-gnu.so
genie/conf/base/exceptions.cpython-35m-x86_64-linux-gnu.so
genie/conf/base/interface.cpython-35m-x86_64-linux-gnu.so
genie/conf/base/link.cpython-35m-x86_64-linux-gnu.so
genie/conf/base/sprinkler.cpython-35m-x86_64-linux-gnu.so
genie/conf/base/testbed.cpython-35m-x86_64-linux-gnu.so
genie/conf/base/utils.cpython-35m-x86_64-linux-gnu.so
genie/conf/base/warnings.cpython-35m-x86_64-linux-gnu.so
genie/conf/base/loader/__init__.py
genie/conf/utils/__init__.py
genie/conf/utils/converter.cpython-35m-x86_64-linux-gnu.so
genie.conf-19.12.dist-info/METADATA
genie.conf-19.12.dist-info/WHEEL
genie.conf-19.12.dist-info/namespace_packages.txt
genie.conf-19.12.dist-info/top_level.txt
genie.conf-19.12.dist-info/RECORD
